{
    "name": "Isle of Dogs",
    "Rating:": "PG-13(ThematicElements|SomeViolentImages)",
    "Genre:": "Comedy,Adventure",
    "Original Language:": "English",
    "Director:": "WesAnderson",
    "Producer:": "WesAnderson,ScottRudin,StevenRales,JeremyDawson",
    "Writer:": "WesAnderson",
    "Release Date (Theaters):": "Apr6,2018\u00a0wide",
    "Release Date (Streaming):": "Jul17,2018",
    "Box Office (Gross USA):": "$31.9M",
    "Runtime:": "1h41m",
    "Distributor:": "FoxSearchlight",
    "Sound Mix:": "DolbyDigital",
    "Aspect Ratio:": "Scope(2.35:1)"
}